ScribeLog/__init__.py
ScribeLog/exception.py
ScribeLog/logger_module.py
ScribeLog-0.1.0.dist-info/LICENSE
ScribeLog-0.1.0.dist-info/METADATA
ScribeLog-0.1.0.dist-info/WHEEL
ScribeLog-0.1.0.dist-info/top_level.txt
ScribeLog-0.1.0.dist-info/RECORD
