Metadata-Version: 2.2
Name: ScribeLog
Version: 0.1.0
Summary: A lightweight Python library for logging messages to text files.
Home-page: https://github.com/rosebudsystems/ScribeLog
Author: RosebudSystems
Author-email: ale.javier.romero@gmail.com
Classifier: Programming Language :: Python :: 3
Classifier: License :: OSI Approved :: MIT License
Classifier: Operating System :: OS Independent
Requires-Python: >=3.6
License-File: LICENSE
Dynamic: author
Dynamic: author-email
Dynamic: classifier
Dynamic: description
Dynamic: description-content-type
Dynamic: home-page
Dynamic: requires-python
Dynamic: summary
